evotool/__init__.py
evotool/evo_method/__init__.py
evotool/evo_method/base_config.py
evotool/evo_method/base_method.py
evotool/evo_method/base_run_state_dict.py
evotool/evo_method/eoh/__init__.py
evotool/evo_method/eoh/eoh.py
evotool/evo_method/eoh/run_config.py
evotool/evo_method/eoh/run_state_dict.py
evotool/evo_method/es_1p1/__init__.py
evotool/evo_method/es_1p1/es_1p1.py
evotool/evo_method/es_1p1/run_config.py
evotool/evo_method/es_1p1/run_state_dict.py
evotool/evo_method/evoengineer/__init__.py
evotool/evo_method/evoengineer/evoengineer.py
evotool/evo_method/evoengineer/run_config.py
evotool/evo_method/evoengineer/run_state_dict.py
evotool/evo_method/funsearch/__init__.py
evotool/evo_method/funsearch/funsearch.py
evotool/evo_method/funsearch/island.py
evotool/evo_method/funsearch/programs_database.py
evotool/evo_method/funsearch/run_config.py
evotool/evo_method/funsearch/run_state_dict.py
evotool/task/__init__.py
evotool/task/base_task/__init__.py
evotool/task/base_task/base_evaluator.py
evotool/task/base_task/base_method_interface.py
evotool/task/base_task/base_task_config.py
evotool/task/base_task/eoh_interface.py
evotool/task/base_task/es_1p1_interface.py
evotool/task/base_task/evoengineer_interface.py
evotool/task/base_task/funsearch_interface.py
evotool/task/cuda_engineering/__init__.py
evotool/task/cuda_engineering/cuda_evaluator.py
evotool/task/cuda_engineering/cuda_task_config.py
evotool/task/cuda_engineering/eoh_interface.py
evotool/task/cuda_engineering/es_1p1_interface.py
evotool/task/cuda_engineering/evoengineer_interface.py
evotool/task/cuda_engineering/funsearch_interface.py
evotool/task/cuda_engineering/ai_cuda_engineer/__init__.py
evotool/task/cuda_engineering/ai_cuda_engineer/ai_cuda_engineer.py
evotool/task/cuda_engineering/ai_cuda_engineer/prompt_maker.py
evotool/task/cuda_engineering/ai_cuda_engineer/response_parser.py
evotool/task/cuda_engineering/ai_cuda_engineer/run_config.py
evotoolkit-1.0.1.dist-info/METADATA
evotoolkit-1.0.1.dist-info/WHEEL
evotoolkit-1.0.1.dist-info/licenses/LICENSE
evotoolkit-1.0.1.dist-info/RECORD
