Metadata-Version: 2.4
Name: evotoolkit
Version: 1.0.1
Summary: LLM-driven code evolution method library.
Project-URL: Homepage, https://github.com/pgg3/evotool
Project-URL: Repository, https://github.com/pgg3/evotool
Author-email: Ping Guo <pguo6680@gmail.com>
License: MIT
License-File: LICENSE
Keywords: LLM,evolutionary,optimization,toolkit
Classifier: Development Status :: 4 - Beta
Classifier: Intended Audience :: Developers
Classifier: License :: OSI Approved :: MIT License
Classifier: Programming Language :: Python :: 3
Classifier: Programming Language :: Python :: 3.11
Classifier: Programming Language :: Python :: 3.12
Requires-Python: >=3.11
Requires-Dist: jupyterlab>=4.4.7
Requires-Dist: matplotlib>=3.10.6
Requires-Dist: natsort
Requires-Dist: numpy
Requires-Dist: portalocker
Requires-Dist: scipy
Requires-Dist: setuptools
Provides-Extra: cuda-engineering
Requires-Dist: ninja; extra == 'cuda-engineering'
Requires-Dist: psutil; extra == 'cuda-engineering'
Requires-Dist: torch; extra == 'cuda-engineering'
